{
    "water": [
        {"101/1": 299},
        {"102/1": 1971},
        {"103/1": 1818},
        {"104/1": 693},
        {"105/1": 249},
        {"106/1": 12},
        {"107/1": 341},
        {"108/1": 2789},
        {"109/1": 0},
        {"110/1": 64},
        {"111/1": 29},
        {"112/1": 3122},
        {"113/1": 760},
        {"114/1": 287},
        {"115/1": 560},
        {"201/1": 480},
        {"202/1": 2119},
        {"203/1": 229},
        {"204/1": 364},
        {"205/1": 832},
        {"206/1": 776},
        {"207/1": 1521},
        {"208/1": 941},
        {"209/1": 674},
        {"210/1": 292},
        {"211/1": 1798},
        {"212/1": 1708},
        {"213/1": 1310},
        {"214/1": 1855},
        {"215/1": 128},
        {"301/1": 2598},
        {"302/1": 2296},
        {"303/1": 28},
        {"304/1": 729},
        {"305/1": 2273},
        {"306/1": 397},
        {"307/1": 2929},
        {"308/1": 575},
        {"309/1": 340},
        {"310/1": 1782},
        {"311/1": 2279},
        {"312/1": 126},
        {"313/1": 563},
        {"314/1": 61},
        {"315/1": 839},
        {"401/1": 2023},
        {"402/1": 1986},
        {"403/1": 1759},
        {"404/1": 129},
        {"405/1": 72},
        {"406/1": 73},
        {"407/1": 1525},
        {"408/1": 515},
        {"409/1": 12},
        {"410/1": 2255},
        {"411/1": 2041},
        {"412/1": 291},
        {"413/1": 330},
        {"414/1": 2409},
        {"415/1": 2213},
        {"101/2": 401},
        {"102/2": 518},
        {"103/2": 585},
        {"104/2": 643},
        {"105/2": 770},
        {"106/2": 1930},
        {"107/2": 285},
        {"108/2": 706},
        {"109/2": 761},
        {"110/2": 2065},
        {"111/2": 174},
        {"112/2": 439},
        {"113/2": 289},
        {"114/2": 83},
        {"115/2": 618},
        {"201/2": 391},
        {"202/2": 221},
        {"203/2": 64},
        {"204/2": 609},
        {"205/2": 564},
        {"206/2": 336},
        {"207/2": 958},
        {"208/2": 2103},
        {"209/2": 319},
        {"210/2": 385},
        {"211/2": 81},
        {"212/2": 516},
        {"213/2": 332},
        {"214/2": 85},
        {"215/2": 97},
        {"301/2": 359},
        {"302/2": 1036},
        {"303/2": 91},
        {"304/2": 247},
        {"305/2": 402},
        {"306/2": 421},
        {"307/2": 102},
        {"308/2": 289},
        {"309/2": 277},
        {"310/2": 391},
        {"311/2": 136},
        {"312/2": 1001},
        {"313/2": 704},
        {"314/2": 328},
        {"315/2": 359},
        {"401/2": 1090},
        {"402/2": 217},
        {"403/2": 927},
        {"404/2": 186},
        {"405/2": 458},
        {"406/2": 278},
        {"407/2": 49},
        {"408/2": 597},
        {"409/2": 678},
        {"410/2": 177},
        {"411/2": 353},
        {"412/2": 310},
        {"413/2": 983},
        {"414/2": 360},
        {"415/2": 197}
    ],
    "electric": [
        {"101/1": 5780},
        {"102/1": 4179},
        {"103/1": 2678},
        {"104/1": 8589},
        {"105/1": 3834},
        {"106/1": 6695},
        {"107/1": 1434},
        {"108/1": 41},
        {"109/1": 0},
        {"110/1": 3186},
        {"111/1": 4438},
        {"112/1": 6320},
        {"113/1": 5528},
        {"114/1": 0},
        {"115/1": 0},
        {"201/1": 5989},
        {"202/1": 790},
        {"203/1": 7743},
        {"204/1": 6328},
        {"205/1": 9479},
        {"206/1": 1498},
        {"207/1": 8745},
        {"208/1": 2334},
        {"209/1": 9542},
        {"210/1": 5725},
        {"211/1": 846},
        {"212/1": 1864},
        {"213/1": 8014},
        {"214/1": 3320},
        {"215/1": 4072},
        {"301/1": 7590},
        {"302/1": 9428},
        {"303/1": 8344},
        {"304/1": 6031},
        {"305/1": 264},
        {"306/1": 1626},
        {"307/1": 1876},
        {"308/1": 2353},
        {"309/1": 2558},
        {"310/1": 2458},
        {"311/1": 7098},
        {"312/1": 5214},
        {"313/1": 1190},
        {"314/1": 217},
        {"315/1": 9699},
        {"401/1": 8016},
        {"402/1": 891},
        {"403/1": 3779},
        {"404/1": 8947},
        {"405/1": 2846},
        {"406/1": 2237},
        {"407/1": 1134},
        {"408/1": 7275},
        {"409/1": 4364},
        {"410/1": 2147},
        {"411/1": 6333},
        {"412/1": 1946},
        {"413/1": 6221},
        {"414/1": 5833},
        {"415/1": 189},
        {"101/2": 6120},
        {"102/2": 9786},
        {"103/2": 978},
        {"104/2": 238},
        {"105/2": 9210},
        {"106/2": 7953},
        {"107/2": 1963},
        {"108/2": 3755},
        {"109/2": 9930},
        {"110/2": 2885},
        {"111/2": 3409},
        {"112/2": 9936},
        {"113/2": 2099},
        {"114/2": 9565},
        {"115/2": 925},
        {"201/2": 8175},
        {"202/2": 3953},
        {"203/2": 4474},
        {"204/2": 6184},
        {"205/2": 654},
        {"206/2": 5928},
        {"207/2": 2383},
        {"208/2": 7102},
        {"209/2": 6978},
        {"210/2": 7380},
        {"211/2": 9595},
        {"212/2": 9305},
        {"213/2": 8004},
        {"214/2": 9316},
        {"215/2": 0},
        {"301/2": 5739},
        {"302/2": 2196},
        {"303/2": 8596},
        {"304/2": 652},
        {"305/2": 9640},
        {"306/2": 1157},
        {"307/2": 7799},
        {"308/2": 9088},
        {"309/2": 9337},
        {"310/2": 6837},
        {"311/2": 3482},
        {"312/2": 6018},
        {"313/2": 9910},
        {"314/2": 3958},
        {"315/2": 2042},
        {"401/2": 3394},
        {"402/2": 3064},
        {"403/2": 7300},
        {"404/2": 6704},
        {"405/2": 846},
        {"406/2": 2496},
        {"407/2": 7803},
        {"408/2": 2018},
        {"409/2": 3142},
        {"410/2": 1607},
        {"411/2": 7676},
        {"412/2": 8931},
        {"413/2": 272},
        {"414/2": 1549},
        {"415/2": 548}
    ]
}